{
    "links": [
        {
            "name": "Công cụ paraphrasing tiếng Ả Rập",
            "url": "/vi/arabic-paraphrase-tool"
        },
        {
            "name": "Công cụ paraphrasing Trung Quốc",
            "url": "/vi/chinese-paraphrase-tool"
        },
        {
            "name": "Công cụ paraphrasing Đan Mạch",
            "url": "/vi/danish-paraphrase-tool"
        },
        {
            "name": "Công cụ paraphrasing tiếng Ả Rập",
            "url": "/vi/dutch-paraphrase-tool"
        },
        {
            "name": "Công cụ paraphrasing tiếng Anh",
            "url": "/vi/paraphrasing-tool"
        },
        {
            "name": "Công cụ paraphrasing tiếng Pháp",
            "url": "/vi/french-paraphrase-tool"
        },
        {
            "name": "Công cụ diễn giải tiếng Đức",
            "url": "/vi/german-paraphrase-tool"
        },
        {
            "name": "Công cụ paraphrasing tiếng Hin-ddi",
            "url": "/vi/hindi-paraphrase-tool"
        },
        {
            "name": "công cụ paraphrasing Indonesia",
            "url": "/vi/indonesian-paraphrase-tool"
        },
        {
            "name": "Công cụ paraphrasing Ý",
            "url": "/vi/italian-paraphrase-tool"
        },
        {
            "name": "công cụ paraphrasing Nhật Bản",
            "url": "/vi/japanese-paraphrase-tool"
        },
        {
            "name": "Công cụ paraphrasing Hàn Quốc",
            "url": "/vi/korean-paraphrase-tool"
        },
        {
            "name": "Công cụ paraphrasing Ba Lan",
            "url": "/vi/polish-paraphrase-tool"
        },
        {
            "name": "Công cụ paraphrasing Bồ Đào Nha",
            "url": "/vi/portuguese-paraphrase-tool"
        },
        {
            "name": "Công cụ diễn giải tiếng Nga",
            "url": "/vi/russian-paraphrase-tool"
        },
        {
            "name": "Công cụ paraphrasing tiếng Tây Ban Nha",
            "url": "/vi/spanish-paraphrase-tool"
        },
        {
            "name": "Công cụ paraphrasing Thụy Điển",
            "url": "/vi/swedish-paraphrase-tool"
        },
        {
            "name": "Công cụ paraphrasing Thái",
            "url": "/vi/thai-paraphrase-tool"
        },
        {
            "name": "Công cụ paraphrasing Thổ Nhĩ Kỳ",
            "url": "/vi/turkish-paraphrase-tool"
        },
        {
            "name": "Công cụ paraphrasing Ukranian",
            "url": "/vi/ukranian-paraphrase-tool"
        },
        {
            "name": "Công cụ diễn giải tiếng Việt",
            "url": "/vi/vietnamese-paraphrase-tool"
        }
    ]
}