{
    "Language":"ਪੰਜਾਬੀ",
    "htmlLangAtt": "pa",
    "h1": "ਪੰਜਾਬੀ ਵਾਕ ਅਨੁਵਾਦ ਲਈ ਟੈਗਲਾਗ",
    "h2": "ਵਧੀਆ ਆਨਲਾਈਨ ਸਜ਼ਾ ਅਨੁਵਾਦ",
    "TITLE": "ਪੰਜਾਬੀ ਵਾਕ ਅਨੁਵਾਦ ਲਈ tagalog | ਮੁਫ਼ਤ ਆਨਲਾਈਨ ਆਪਣੇ ਵਾਕਾਂ ਦਾ ਅਨੁਵਾਦ ਕਰੋ",
    "META": "ਆਪਣੇ ਵਾਕਾਂ ਨੂੰ ਟੈਗਲਾਗ ਤੋਂ ਪੰਜਾਬੀ ਵਿੱਚ ਤੁਰੰਤ ਮੁਫਤ ਵਿੱਚ ਅਨੁਵਾਦ ਕਰੋ। ਸਾਡੇ ਕੋਲ ਵਰਤੋਂ ਦੀ ਕੋਈ ਸੀਮਾ ਨਹੀਂ ਹੈ. ਮੁਫ਼ਤ ਲਈ ਬਾਹਰ ਕਰਨ ਦੀ ਕੋਸ਼ਿਸ਼ ਕਰੋ!",
    "imgwidth": "40px",
    "imgheight": "40px",
    "imgalt": "altvalue",
    "TEXTUAL_CONTENT": [
        {
            "priority": 1,
            "logoUrl": "/assets/bulb.svg",
            "header": "ਪੰਜਾਬੀ ਵਾਕ ਅਨੁਵਾਦ ਲਈ ਤੁਰੰਤ ਟੈਗਲਾਗ",
            "content": "ਇਹ ਸੰਦ ਤੁਹਾਨੂੰ ਇੱਕ ਪੂਰਾ ਡਾਟਾਬੇਸ ਪੇਸ਼ ਕਰਦਾ ਹੈ ਤਾਂ ਜੋ ਪੰਜਾਬੀ ਭੇਜਣ ਦੇ ਅਨੁਵਾਦ ਲਈ ਟੈਗਲਾਗ ਨੂੰ ਤੁਰੰਤ ਸਮਝ ਸਕੇ। ਤੇਜ਼ ਅਤੇ ਸਹੀ ਨਤੀਜੇ ਲਈ ਸਿਰਫ ਭੇਜਣ ਪਰਿਵਰਤਕ ਵਿੱਚ ਭੇਜਣ ਟਾਈਪ ਕਰੋ ਅਤੇ ਸਹੀ ਵਿਆਕਰਣ ਬਣਤਰ ਦੇ ਨਾਲ ਆਪਣੇ fingertips 'ਤੇ ਨਤੀਜੇ ਪ੍ਰਾਪਤ ਕਰੋ."
        },
        {
            "priority": 1,
            "logoUrl": "/assets/guaranty.svg",
            "header": "ਆਨਲਾਈਨ ਪੰਜਾਬੀ ਵਾਕ ਅਨੁਵਾਦ ਲਈ ਟੈਗਲਾਗ",
            "content": "ਆਪਣੀ ਸਮੱਗਰੀ ਦਾ ਅਨੁਵਾਦ ਆਨਲਾਈਨ ਟੈਗਲਾਗ ਪੰਜਾਬੀ ਵਿੱਚ ਲਵੋ। ਵਿਦੇਸ਼ੀ ਭਾਸ਼ਾ ਦੇ ਪਾਠ ਨੂੰ ਬਿਨਾਂ ਕਿਸੇ ਸਮੇਂ ਅਤੇ ਮਿਹਨਤ ਨਾਲ ਤੁਰੰਤ ਸਮਝੋ."
        },
        {
            "priority": 1,
            "logoUrl": "/assets/support.svg",
            "header": "ਕੁਝ ਕਦਮ ਵਿੱਚ ਪੰਜਾਬੀ ਨੂੰ ਸਜ਼ਾ ਅਨੁਵਾਦਕ ਤਾਗਾਲਾਗ",
            "content": "ਇਹ ਤੁਹਾਨੂੰ ਸੋਚਿਆ ਵੱਧ ਹੋਰ ਸੌਖਾ ਹੈ. ਬਸ ਆਪਣੇ Fharagraph ਨਕਲ ਕਰੋ ਅਤੇ ਕੁਝ ਸਕਿੰਟ ਵਿੱਚ ਪੰਜਾਬੀ ਨੂੰ tagalog ਵਿੱਚ ਅਨੁਵਾਦ ਪ੍ਰਾਪਤ ਕਰੋ."
        },
        {
            "priority": 1,
            "logoUrl": "/assets/protect.svg",
            "header": "ਪੰਜਾਬੀ ਵਾਕ ਅਨੁਵਾਦ ਲਈ ਮੁਫਤ ਆਨਲਾਈਨ ਟੈਗਲਾਗ",
            "content": "ਮੁਫ਼ਤ ਆਨਲਾਈਨ ਅਨੁਵਾਦਕ punjabi ਨੂੰ tagalog ਅਨੁਵਾਦ ਕਰਨ ਲਈ ਆਪਣੇ ਵਾਰ ਅਤੇ ਪੈਸੇ ਦੀ ਬਚਤ ਕਰਨ ਲਈ. ਸਾਨੂੰ ਧਿਆਨ ਦਿੱਤਾ ਹੈ, ਜੋ ਕਿ ਅਰਥ ਅਤੇ ਜਜ਼ਬਾਤ ਖਤਮ ਹੋ ਨਾ ਕੀਤਾ ਜਾਣਾ ਚਾਹੀਦਾ ਹੈ, ਜਦਕਿ ਪਾਠ ਨੂੰ ਕਿਸੇ ਹੋਰ ਭਾਸ਼ਾ ਵਿੱਚ ਅਨੁਵਾਦ."
        },
        {
            "priority": 1,
            "logoUrl": "/assets/easy.svg",
            "header": "ਪੰਜਾਬੀ ਨੂੰ ਤੁਰੰਤ ਅਤੇ ਲੋੜੀਦੇ ਨਤੀਜੇ ਟੈਗਲਾਗ ਲਵੋ",
            "content": "ਪੰਜਾਬੀ ਨੂੰ ਟੈਗਲਾਗ ਲਈ ਇੱਕ ਜੱਦੀ ਵਰਗੇ ਆਪਣੇ ਲੇਖ ਨੂੰ ਪੇਸ਼ੇਵਰ ਬਣਾਉਣ ਲਈ ਆਨਲਾਈਨ transalator. ਵਾਕ ਅਨੁਵਾਦ ਖਾਸ ਤੌਰ 'ਤੇ ਕਿਸੇ ਵੀ ਭਾਸ਼ਾ ਵਿੱਚ ਸਮਝ ਸੁਨੇਹੇ ਨੂੰ ਬਣਾਉਣ ਲਈ ਤਿਆਰ ਕੀਤਾ ਗਿਆ ਹੈ"
        },
        {
            "priority": 1,
            "logoUrl": "/assets/cloud.svg",
            "header": "ਇਹ ਸੰਦ ਪੰਜਾਬੀ ਵਾਕ ਅਨੁਵਾਦਕਾਂ ਨੂੰ ਟੈਗਲਾਗ ਵਿੱਚ ਨਿਪੁੰਨ ਹੈ।",
            "content": "ਪੰਜਾਬੀ ਨੂੰ ਟੈਗਲਾਗ ਦੇ ਵਾਕ ਅਨੁਵਾਦ ਲਈ ਸੱਭਿਆਚਾਰਕ ਅਤੇ ਭਾਸ਼ਾਈ ਤੱਤਾਂ ਨੂੰ ਧਿਆਨ ਵਿੱਚ ਰੱਖਦੇ ਹੋਏ। ਇਹ ਨਾ ਸਿਰਫ ਵਾਕ ਦਾ ਅਨੁਵਾਦ ਕਰਦਾ ਹੈ, ਇਸ ਨੂੰ ਹੋਰ ਸਮੱਗਰੀ ਨੂੰ ਹੋਰ ਸੁਧਾਰ ਵੱਖ-ਵੱਖ ਦਰਸ਼ਕ ਦੇ ਅਨੁਕੂਲ."
        },
        {
            "priority": 1,
            "logoUrl": "/assets/cloud.svg",
            "header": "ਤੁਹਾਡੀ ਸਮੱਗਰੀ ਨੂੰ ਪੇਸ਼ੇਵਰ ਬਣਾਉਣ ਲਈ ਪੰਜਾਬੀ ਨੂੰ ਟੈਗਲਾਗ ਵਿੱਚ ਵਾਕ ਅਨੁਵਾਦ",
            "content": "ਬਹੁਭਾਸ਼ਾਈ ਵਾਕ ਅਨੁਵਾਦ ਸੰਦ ਕਿਸੇ ਵੀ ਭਾਸ਼ਾ ਵਿੱਚ ਵਾਕਾਂ ਦਾ ਅਨੁਵਾਦ ਕਰਨ ਲਈ ਇਹ ਪੰਜਾਬੀ ਲਈ ਟੈਗਲਾਗ ਹੋ ਸਕਦਾ ਹੈ। ਬਸ ਵਾਕ ਕਨਵਰਟਰ ਵਿੱਚ ਸਜ਼ਾ ਟਾਈਪ ਕਰੋ ਅਤੇ ਸਹੀ ਵਿਆਕਰਣ structureਾਂਚੇ ਦੇ ਨਾਲ ਆਪਣੀਆਂ ਉਂਗਲੀਆਂ 'ਤੇ ਨਤੀਜਾ ਪ੍ਰਾਪਤ ਕਰੋ."
        },
        {
            "priority": 1,
            "logoUrl": "/assets/cloud.svg",
            "header": "ਇਹ ਅਡਵਾਂਸਡ ਟੂਲ ਲੇਖਾਂ, ਕਹਾਣੀਆਂ ਅਤੇ ਕਵਿਤਾਵਾਂ ਨੂੰ ਟੈਗਲਾਗ ਵਿਚ ਇਕ ਹੋਰ ਭਾਸ਼ਾ ਵਿਚ ਪਾਠ ਦਾ ਅਨੁਵਾਦ ਕਰਦੇ ਹੋਏ ਅਰਥ ਅਤੇ ਭਾਵਨਾ ਨੂੰ ਖੋਲ੍ਹ ਕੇ ਪੰਜਾਬੀ ਵਿਚ ਬਦਲਦਾ ਹੈ.",
            "content": "ਜਾਂ ਤਾਂ ਇਹ ਲੇਖ ਜਾਂ ਕਹਾਣੀਆਂ ਹਨ ਜੋ ਅਸੀਂ ਟੈਗਲਾਗ ਨੂੰ ਪੰਜਾਬੀ ਵਿੱਚ ਅਨੁਵਾਦ ਕਰਦੇ ਹਾਂ. ਇਹ ਸਾਧਨ ਸ਼ਬਦ ਦੁਆਰਾ ਸ਼ਬਦ ਦਾ ਅਨੁਵਾਦ ਨਹੀਂ ਕਰਦਾ. ਬੁੱਧੀਮਾਨ, ਫੈਸਲੇ ਲੈਣ ਵਾਲੇ ਸਾੱਫਟਵੇਅਰ ਦੇ ਨਾਲ ਇਹ ਫੈਸਲਾ ਕਰਦਾ ਹੈ ਕਿ ਕਿਹੜੇ ਸ਼ਬਦਾਂ ਦੀ ਵਰਤੋਂ ਕਰਨੀ ਹੈ ਅਤੇ ਕਿਹੜੇ ਲੋਕਾਂ ਨੂੰ ਨਫ਼ਰਤ ਕਰਨੀ ਹੈ. ਅਸੀਂ ਧਿਆਨ ਕੇਂਦ੍ਰਤ ਕੀਤਾ ਹੈ ਕਿ ਕਿਸੇ ਹੋਰ ਭਾਸ਼ਾ ਵਿੱਚ ਪਾਠ ਦਾ ਅਨੁਵਾਦ ਕਰਦੇ ਹੋਏ ਅਰਥ ਅਤੇ ਭਾਵਨਾਵਾਂ ਨੂੰ ਖਤਮ ਨਹੀਂ ਕੀਤਾ ਜਾਣਾ ਚਾਹੀਦਾ."
        },
        {
            "priority": 1,
            "logoUrl": "/assets/cloud.svg",
            "header": "ਅਸੀਂ ਹਵਾਲੇ ਟੈਗਲਾਗ ਨੂੰ ਪੰਜਾਬੀ ਵਿੱਚ ਅਨੁਵਾਦ ਕਰਦੇ ਹਾਂ, ਅਤੇ ਇਸਦੇ ਉਲਟ, ਅਰਥ ਨੂੰ ਬਦਲਿਆ ਨਹੀਂ ਰੱਖਦੇ ਹੋਏ।",
            "content": "ਕਈ ਵਾਰ ਹਵਾਲਾ ਪੰਜਾਬੀ ਨੂੰ tagalog ਵਿੱਚ ਤਬਦੀਲੀ ਦੇ ਵੇਲੇ 'ਤੇ ਤਬਦੀਲ. ਸਜ਼ਾ ਅਨੁਵਾਦ ਦੇ ਇਕਾਈ ਦਾ ਸੱਚ ਹੈ, ਅਰਥ ਨੂੰ ਤਬਦੀਲ ਰੱਖਣ ਲਈ ਖਾਸ ਤੌਰ 'ਤੇ ਹੁੰਦਾ ਹੈ. ਐਡਵਾਂਸਡ ਏਆਈ ਦੇ ਨਾਲ ਇਹ ਨਾ ਸਿਰਫ ਵਾਕ ਦਾ ਅਨੁਵਾਦ ਕਰਦਾ ਹੈ ਇਸ ਨੂੰ ਵੱਖੋ ਵੱਖਰੇ ਦਰਸ਼ਕਾਂ ਦੇ ਅਨੁਕੂਲ ਸਮੱਗਰੀ ਨੂੰ ਹੋਰ ਸੁਧਾਰਦਾ ਹੈ."
        }
    ],
    "csscdns": [
        "<link rel=\"stylesheet\" href=\"/css/file-upload.css\" />"
    ]
}