{
    "Language":"አማርኛ",
    "htmlLangAtt": "am",
    "h1": "ከፒንዪን ወደ አማርኛ ዓረፍተ ነገር ትርጉም",
    "h2": "ምርጥ የመስመር ላይ አረፍተ ነገር ትርጉም",
    "TITLE": "ፒንዪን ወደ አማርኛ ዓረፍተ ነገር ትርጉም | ዓረፍተ ነገሮችዎን በኢንተርኔት",
    "META": "ዓረፍተ ነገሮችዎን ከፒንዪን ወደ አማርኛ በቅጽበት በነፃ ይተርጉሙት። ምንም የአጠቃቀም ገደብ የለንም። በነጻ ይሞክሩ!",
    "imgwidth": "40px",
    "imgheight": "40px",
    "imgalt": "altvalue",
    "TEXTUAL_CONTENT": [
        {
            "priority": 1,
            "logoUrl": "/assets/bulb.svg",
            "header": "ፈጣን ፒንዪን ወደ አማርኛ ዓረፍተ ነገር ትርጉም",
            "content": "ይህ መሣሪያ ወዲያውኑ ወደ አማርኛ መጠየቂያ ትርጉም pinyin ለመረዳት የሚሆን ሙሉ ጎታ ማቅረብ። ለፈጣን እና ትክክለኛ ውጤት የቃላትን መለወጫ ውስጥ ብቻ ይተይቡ እና በትክክለኛው ሰዋሰዋዊ መዋቅር በጣቶችዎ ላይ ውጤትን ያግኙ።"
        },
        {
            "priority": 1,
            "logoUrl": "/assets/guaranty.svg",
            "header": "ፒንዪን ወደ አማርኛ ዓረፍተ ነገር ትርጉም በመስመር ላይ",
            "content": "ይዘትዎን በኢንተርኔት ፒንዪን ወደ አማርኛ የተተረጎመ ያግኙ። የውጭውን ቋንቋ ጽሑፍ ወዲያውኑ ያለ ጊዜ እና ጥረት ይረዱ።"
        },
        {
            "priority": 1,
            "logoUrl": "/assets/support.svg",
            "header": "አረፍተ ነገር ተርጓሚ ፒንዪን ወደ አማርኛ በጥቂት ደረጃዎች",
            "content": "እርስዎ ካሰቡት በላይ ቀላል ነው። ፈርማችሁን ብቻ ገልብጠው በጥቂት ሰከንዶች ውስጥ በፒንዪን ወደ አማርኛ መተርጎም ያግኙ።"
        },
        {
            "priority": 1,
            "logoUrl": "/assets/protect.svg",
            "header": "ነፃ የመስመር ላይ ፒንዪን ወደ አማርኛ ዓረፍተ ነገር ትርጉም",
            "content": "ፒንዪን ወደ አማርኛ ለመተርጎም ጊዜዎን እና ገንዘብዎን ለመቆጠብ ነፃ የመስመር ላይ ተርጓሚ. ጽሑፉን በሌላ ቋንቋ ሲተረጉሙ ትርጉሙ እና ስሜቱ ሊጠፋ እንደሌለበት አተኩረናል።"
        },
        {
            "priority": 1,
            "logoUrl": "/assets/easy.svg",
            "header": "ፈጣን እና የተፈለገውን ውጤት ያግኙ pinyin ወደ አማርኛ",
            "content": "ኦንላይን ተርጓሚ ለፒንዪን ወደ አማርኛ ጽሁፍዎን እንደ ተወላጅ ሰው ሙያዊ ለማድረግ። የዓረፍተ ነገር ትርጉም በተለይ መልእክቱን በማንኛውም ቋንቋ እንዲረዳ ለማድረግ የተነደፈ ነው"
        },
        {
            "priority": 1,
            "logoUrl": "/assets/cloud.svg",
            "header": "ይህ መሣሪያ የአማርኛ ዓረፍተ ተርጓሚዎች ፒንዪን ውስጥ ብቃት ያለው ነው።",
            "content": "የፒንዪን ትርጉም ወደ አማርኛ ለመተርጎም የባህላዊና የቋንቋ አባላትን ግምት ውስጥ ማስገባት። ይህ ብቻ ሳይሆን ተጨማሪ የተለያዩ ታዳሚዎች የሚስማሙ ይዘት ለማጥራት ዓረፍተ ነገር ይተረጉመዋል።"
        },
        {
            "priority": 1,
            "logoUrl": "/assets/cloud.svg",
            "header": "የዓረፍተ ነገር ትርጉም በፒንዪን ወደ አማርኛ ይዘትዎን ሙያዊ ለማድረግ",
            "content": "ዓረፍተ ነገርን ወደ ማንኛውም ቋንቋ ለመተርጎም ብዙ ቋንቋ ዓረፍተ ነገር ትርጉም መሳሪያ ፒንዪን ወደ አማርኛ ሊሆን ይችላል። በአረፍተ ነገር መለወጫ ውስጥ ያለውን ዓረፍተ ነገር ይተይቡ እና በትክክለኛ ሰዋሰዋዊ መዋቅር በጣቶችዎ ላይ ውጤትን ያግኙ።"
        },
        {
            "priority": 1,
            "logoUrl": "/assets/cloud.svg",
            "header": "ይህ የላቀ መሳሪያ ጽሁፉን በሌላ ቋንቋ ሲተረጉሙ ትርጉምና ስሜትን ሳይቀይሩ ጽሁፎችን፣ ታሪኮችንና ግጥሞችን በፒንዪን ወደ አማርኛ ይቀይራል።",
            "content": "ወይ ፒንዪን ወደ አማርኛ የምንተረጎመው ጽሁፍ ወይም ታሪኮች ነው። ይህ መሳሪያ ቃልን በቃል አይተረጎምም። በማሰብ ችሎታ, ውሳኔ አሰጣጥ ሶፍትዌር የትኞቹ ቃላትን መጠቀም እንዳለባቸው እና የትኞቹ ችላ እንደሚሉ ይወስናል. ጽሑፉን በሌላ ቋንቋ በመተርጎም ትርጉሙ እና ስሜቱ ሊጠፋ እንደማይገባ አተኩረናል።"
        },
        {
            "priority": 1,
            "logoUrl": "/assets/cloud.svg",
            "header": "ጥቅሶችን ፒንዪን ወደ አማርኛ እንተረጉማለን፤ በተቃራኒው ደግሞ ትርጉሙን ሳይለወጥ እያቆየን ነው።",
            "content": "አንዳንድ ጊዜ ጥቅሶች በፒንዪን ወደ አማርኛ በሚለዋወጡበት ጊዜ ይለዋወጣሉ። የአረፍተ ነገር ትርጉም ትርጉሙ ትክክለኛውን ትርጉም ሳይለወጥ ለመጠበቅ ነው። የላቀ AI ጋር ብቻ ሳይሆን ተጨማሪ የተለያዩ ታዳሚዎች የሚስማሙ ይዘት ለማጥራት ዓረፍተ ነገር ይተረጉመዋል።"
        }
    ],
    "csscdns": [
        "<link rel=\"stylesheet\" href=\"/css/file-upload.css\" />"
    ],
    "jsfilepaths":[
        "/js/translation.js"
    ]
}